odoo/addons/ssi_accountant_general_audit_ws_ra210/README.rst
odoo/addons/ssi_accountant_general_audit_ws_ra210/__init__.py
odoo/addons/ssi_accountant_general_audit_ws_ra210/__manifest__.py
odoo/addons/ssi_accountant_general_audit_ws_ra210/data/accountant_general_audit_worksheet_conclusion_data.xml
odoo/addons/ssi_accountant_general_audit_ws_ra210/data/accountant_general_audit_worksheet_type_data.xml
odoo/addons/ssi_accountant_general_audit_ws_ra210/data/approval_template_data.xml
odoo/addons/ssi_accountant_general_audit_ws_ra210/data/ir_sequence_data.xml
odoo/addons/ssi_accountant_general_audit_ws_ra210/data/policy_template_data.xml
odoo/addons/ssi_accountant_general_audit_ws_ra210/data/sequence_template_data.xml
odoo/addons/ssi_accountant_general_audit_ws_ra210/models/__init__.py
odoo/addons/ssi_accountant_general_audit_ws_ra210/models/accountant_general_audit_standard_detail.py
odoo/addons/ssi_accountant_general_audit_ws_ra210/models/ws_ra210.py
odoo/addons/ssi_accountant_general_audit_ws_ra210/models/ws_ra210_account_inherent_risk.py
odoo/addons/ssi_accountant_general_audit_ws_ra210/security/ir.model.access.csv
odoo/addons/ssi_accountant_general_audit_ws_ra210/security/ir_module_category_data.xml
odoo/addons/ssi_accountant_general_audit_ws_ra210/security/ir_rule_data.xml
odoo/addons/ssi_accountant_general_audit_ws_ra210/security/res_group_data.xml
odoo/addons/ssi_accountant_general_audit_ws_ra210/static/description/icon.png
odoo/addons/ssi_accountant_general_audit_ws_ra210/views/accountant_general_audit_standard_detail_views.xml
odoo/addons/ssi_accountant_general_audit_ws_ra210/views/ws_ra210_account_inherent_risk_views.xml
odoo/addons/ssi_accountant_general_audit_ws_ra210/views/ws_ra210_views.xml
odoo14_addon_ssi_accountant_general_audit_ws_ra210-14.0.1.3.2.dev1.dist-info/METADATA
odoo14_addon_ssi_accountant_general_audit_ws_ra210-14.0.1.3.2.dev1.dist-info/WHEEL
odoo14_addon_ssi_accountant_general_audit_ws_ra210-14.0.1.3.2.dev1.dist-info/top_level.txt
odoo14_addon_ssi_accountant_general_audit_ws_ra210-14.0.1.3.2.dev1.dist-info/RECORD
